LICENSE
MANIFEST.in
README.md
setup.cfg
setup.py
google/cloud/jupyter_config/__init__.py
google/cloud/jupyter_config/config.py
google/cloud/jupyter_config/config_test.py
google/cloud/jupyter_config/tokenrenewer.py
google_cloud_jupyter_config.egg-info/PKG-INFO
google_cloud_jupyter_config.egg-info/SOURCES.txt
google_cloud_jupyter_config.egg-info/dependency_links.txt
google_cloud_jupyter_config.egg-info/requires.txt
google_cloud_jupyter_config.egg-info/top_level.txt
jupyter-config/jupyter_server_config.d/google_cloud_jupyter_config.json