Metadata-Version: 2.4
Name: google-cloud-jupyter-config
Version: 0.0.11
Summary: Jupyter configuration utilities using gcloud
Home-page: https://github.com/GoogleCloudPlatform/jupyter-extensions/tree/master/google-cloud-jupyter-config
Author: Google, Inc.
License: Apache License 2.0
Requires-Python: >=3.8
License-File: LICENSE
Requires-Dist: cachetools
Requires-Dist: jupyter_server>=2.4.0
Requires-Dist: traitlets
Dynamic: author
Dynamic: description
Dynamic: description-content-type
Dynamic: home-page
Dynamic: license
Dynamic: license-file
Dynamic: requires-dist
Dynamic: requires-python
Dynamic: summary
